main.py
dami_h_test_uv-0.2.0.dist-info/METADATA
dami_h_test_uv-0.2.0.dist-info/WHEEL
dami_h_test_uv-0.2.0.dist-info/top_level.txt
dami_h_test_uv-0.2.0.dist-info/RECORD
