Metadata-Version: 2.4
Name: dami_h-test-uv
Version: 0.2.0
Summary: BIO Here
Requires-Python: >=3.14
Requires-Dist: numpy>=2.3.4
Requires-Dist: pandas>=2.3.3
